{"nodes": [{"id": "templates_base_base_sablon", "label": "base.html ortak taban \u015fablon", "file_type": "document", "source_file": "templates/base.html", "source_location": null, "source_url": null, "captured_at": null, "author": null, "contributor": null}, {"id": "templates_base_notification_popup_include", "label": "notification_popup.html include", "file_type": "concept", "source_file": "templates/base.html", "source_location": null, "source_url": null, "captured_at": null, "author": null, "contributor": null}, {"id": "templates_base_app_shell_js", "label": "app-shell.js (toast/confirm/refresh-manager)", "file_type": "concept", "source_file": "templates/base.html", "source_location": null, "source_url": null, "captured_at": null, "author": null, "contributor": null}, {"id": "templates_base_dark_mode_bootstrap", "label": "Dark-mode erken localStorage inline scripti", "file_type": "concept", "source_file": "templates/base.html", "source_location": null, "source_url": null, "captured_at": null, "author": null, "contributor": null}], "edges": [{"source": "templates_base_base_sablon", "target": "templates_base_notification_popup_include", "relation": "references", "confidence": "EXTRACTED", "confidence_score": 1.0, "source_file": "templates/base.html", "source_location": "base.html:46", "weight": 1.0}, {"source": "templates_base_base_sablon", "target": "templates_base_app_shell_js", "relation": "references", "confidence": "EXTRACTED", "confidence_score": 1.0, "source_file": "templates/base.html", "source_location": "base.html:36", "weight": 1.0}, {"source": "templates_base_base_sablon", "target": "memory_2026_07_09_ortak_css_faz1_ve_db_tuneli_gullu_common_css", "relation": "references", "confidence": "EXTRACTED", "confidence_score": 1.0, "source_file": "templates/base.html", "source_location": "base.html:16", "weight": 1.0}, {"source": "templates_base_base_sablon", "target": "templates_base_dark_mode_bootstrap", "relation": "references", "confidence": "EXTRACTED", "confidence_score": 1.0, "source_file": "templates/base.html", "source_location": "base.html:5", "weight": 1.0}], "hyperedges": [{"id": "base_html_extending_pages_faz1", "label": "base.html'i extend eden Faz 1 sayfalar\u0131", "nodes": ["templates_base_base_sablon", "templates_akilli_motor_akilli_komisyon_motoru", "templates_approve_users_kullanici_onay", "templates_archive_arsiv_sayfasi", "templates_bulk_order_prepare_toplu_urun_hazirla", "templates_cihazlarim_cihazlarim", "templates_degisim_talep_degisim_listesi", "templates_flas_indirim_flas_indirim_motoru", "templates_home_anasayfa", "templates_iade_listesi_iade_listesi", "templates_image_manager_urun_gorsel_yoneticisi"], "relation": "participate_in", "confidence": "EXTRACTED", "confidence_score": 1.0, "source_file": "templates/base.html"}]}